redfs/__init__.py
redfs/__version__.py
redfs/esl.py
redfs-0.0.4.dev1.dist-info/LICENSE
redfs-0.0.4.dev1.dist-info/METADATA
redfs-0.0.4.dev1.dist-info/WHEEL
redfs-0.0.4.dev1.dist-info/top_level.txt
redfs-0.0.4.dev1.dist-info/RECORD
