Metadata-Version: 2.1
Name: redfs
Version: 0.0.4.dev1
Summary: Pure Python3 with Gevent implement the FreeSWITCH Event Socket Protocol Client
Home-page: https://github.com/hnimminh/redfs
Author: Minh Minh
Author-email: hnimminh@outlook.com
License: MIT
Platform: UNKNOWN
Classifier: Development Status :: 4 - Beta
Classifier: Intended Audience :: Developers
Classifier: Programming Language :: Python
Classifier: License :: OSI Approved :: MIT License
Classifier: Programming Language :: Python :: 3
Classifier: Programming Language :: Python :: 3.6
Classifier: Programming Language :: Python :: 3.7
Classifier: Programming Language :: Python :: 3.8
Classifier: Programming Language :: Python :: 3.9
License-File: LICENSE
Requires-Dist: gevent
